How2jJ2eeJiaocheng/README.md
How2jJ2eeJiaocheng/__init__.py
How2jJ2eeJiaocheng/__main__.py
How2jJ2eeJiaocheng/file.epub
How2jJ2eeJiaocheng/index.html
How2jJ2eeJiaocheng/css/__init__.py
How2jJ2eeJiaocheng/css/annotations.css
How2jJ2eeJiaocheng/css/main.css
How2jJ2eeJiaocheng/css/normalize.css
How2jJ2eeJiaocheng/css/popup.css
How2jJ2eeJiaocheng/font/__init__.py
How2jJ2eeJiaocheng/font/fontello.eot
How2jJ2eeJiaocheng/font/fontello.svg
How2jJ2eeJiaocheng/font/fontello.ttf
How2jJ2eeJiaocheng/font/fontello.woff
How2jJ2eeJiaocheng/img/__init__.py
How2jJ2eeJiaocheng/img/annotator-glyph-sprite.png
How2jJ2eeJiaocheng/img/annotator-icon-sprite.png
How2jJ2eeJiaocheng/img/apple-touch-icon.png
How2jJ2eeJiaocheng/img/cancelfullscreen.png
How2jJ2eeJiaocheng/img/close.png
How2jJ2eeJiaocheng/img/fullscreen.png
How2jJ2eeJiaocheng/img/loader.gif
How2jJ2eeJiaocheng/img/menu-icon.png
How2jJ2eeJiaocheng/img/save.png
How2jJ2eeJiaocheng/img/saved.png
How2jJ2eeJiaocheng/img/settings-s.png
How2jJ2eeJiaocheng/img/settings.png
How2jJ2eeJiaocheng/img/star.png
How2jJ2eeJiaocheng/js/__init__.py
How2jJ2eeJiaocheng/js/epub.js
How2jJ2eeJiaocheng/js/epub.min.js
How2jJ2eeJiaocheng/js/epub.min.map
How2jJ2eeJiaocheng/js/hooks.min.js
How2jJ2eeJiaocheng/js/hooks.min.map
How2jJ2eeJiaocheng/js/reader.js
How2jJ2eeJiaocheng/js/reader.js.map
How2jJ2eeJiaocheng/js/reader.min.js
How2jJ2eeJiaocheng/js/reader.min.map
How2jJ2eeJiaocheng/js/hooks/__init__.py
How2jJ2eeJiaocheng/js/hooks/extensions/__init__.py
How2jJ2eeJiaocheng/js/hooks/extensions/highlight.js
How2jJ2eeJiaocheng/js/libs/__init__.py
How2jJ2eeJiaocheng/js/libs/jquery.min.js
How2jJ2eeJiaocheng/js/libs/localforage.min.js
How2jJ2eeJiaocheng/js/libs/screenfull.js
How2jJ2eeJiaocheng/js/libs/screenfull.min.js
How2jJ2eeJiaocheng/js/libs/zip.min.js
How2jJ2eeJiaocheng/js/plugins/__init__.py
How2jJ2eeJiaocheng/js/plugins/hypothesis.js
How2jJ2eeJiaocheng/js/plugins/search.js
how2j_j2ee_jiaocheng-2024.3.5.0.dist-info/METADATA
how2j_j2ee_jiaocheng-2024.3.5.0.dist-info/WHEEL
how2j_j2ee_jiaocheng-2024.3.5.0.dist-info/entry_points.txt
how2j_j2ee_jiaocheng-2024.3.5.0.dist-info/top_level.txt
how2j_j2ee_jiaocheng-2024.3.5.0.dist-info/RECORD
